jsoneng/__init__.py
jsoneng-1.0.8.dist-info/LICENSE
jsoneng-1.0.8.dist-info/METADATA
jsoneng-1.0.8.dist-info/WHEEL
jsoneng-1.0.8.dist-info/top_level.txt
jsoneng-1.0.8.dist-info/RECORD
