Metadata-Version: 2.1
Name: jsoneng
Version: 1.0.8
Summary: A package for a python JSON database CRUD engine
Home-page: https://github.com/youhengzhou/jsoneng
Author: YouHeng Zhou
Author-email: youhengzhou@cmail.carleton.ca
Project-URL: Bug Tracker, https://github.com/youhengzhou/jsoneng/issues
Classifier: Programming Language :: Python :: 3
Classifier: License :: OSI Approved :: MIT License
Classifier: Operating System :: OS Independent
Requires-Python: >=3.6
License-File: LICENSE
